mobileprovision/__init__.py
mobileprovision/command.py
mobileprovision/parser.py
mobileprovision/util.py
PyMobileProvision-1.4.6.dist-info/LICENSE
PyMobileProvision-1.4.6.dist-info/METADATA
PyMobileProvision-1.4.6.dist-info/WHEEL
PyMobileProvision-1.4.6.dist-info/entry_points.txt
PyMobileProvision-1.4.6.dist-info/top_level.txt
PyMobileProvision-1.4.6.dist-info/RECORD
