Metadata-Version: 2.1
Name: PyMobileProvision
Version: 1.4.6
Summary: Python3, parse ".mobileprovision" file in MacOS System;
Home-page: https://github.com/shede333/PyMobileProvision
Author: shede333
Author-email: 333wshw@163.com
License: UNKNOWN
Keywords: mobileprovision mobile provision MobileProvision profile profiles
Platform: UNKNOWN
Classifier: Development Status :: 5 - Production/Stable
Classifier: Natural Language :: Chinese (Simplified)
Classifier: License :: OSI Approved :: MIT License
Classifier: Operating System :: MacOS :: MacOS X
Classifier: Operating System :: POSIX
Classifier: Topic :: Software Development :: Libraries :: Python Modules
Classifier: Programming Language :: Python
Classifier: Programming Language :: Python :: 3
Classifier: Programming Language :: Python :: 3.6
Classifier: Programming Language :: Python :: 3.7
Classifier: Programming Language :: Python :: 3.8
Requires-Python: ~=3.6
License-File: LICENSE
Requires-Dist: cryptography (>=36.0)
